twitterpersona/__init__.py
twitterpersona/generate_word_cloud.py
twitterpersona/load_twitter_msg.py
twitterpersona/preprocessing.py
twitterpersona/sentiment_analysis.py
twitterpersona/twitterLogo.png
twitterpersona-0.3.8.dist-info/METADATA
twitterpersona-0.3.8.dist-info/WHEEL
twitterpersona-0.3.8.dist-info/LICENSE
twitterpersona-0.3.8.dist-info/RECORD
