Metadata-Version: 2.1
Name: twitterpersona
Version: 0.3.8
Summary: Assess whether a twitter is positive or negative based on the user's recent tweets
License: MIT
Author: Andy Wang, Renzo Wijngaarden, Roan Raina, Yurui Feng
Requires-Python: >=3.9,<4.0
Classifier: License :: OSI Approved :: MIT License
Classifier: Programming Language :: Python :: 3
Classifier: Programming Language :: Python :: 3.9
Classifier: Programming Language :: Python :: 3.10
Classifier: Programming Language :: Python :: 3.11
Requires-Dist: matplotlib (>=3.6.3,<4.0.0)
Requires-Dist: nltk (>=3.8.1,<4.0.0)
Requires-Dist: numpy (>=1.24.1,<2.0.0)
Requires-Dist: pandas (>=1.5.2,<2.0.0)
Requires-Dist: pillow (>=9.4.0,<10.0.0)
Requires-Dist: python-dotenv (>=0.21.0,<0.22.0)
Requires-Dist: requests (>=2.28.2,<3.0.0)
Requires-Dist: tweepy (>=4.12.1,<5.0.0)
Requires-Dist: tweet-preprocessor (>=0.6.0,<0.7.0)
Requires-Dist: urllib3 (>=1.26.14,<2.0.0)
Requires-Dist: wordcloud (>=1.8.2.2,<2.0.0.0)
